{
    "始终不渝": 9,
    "纸上谈兵": 5,
    "白驹过隙": 3,
    "生生不息": 2,
    "下不为例": 2,
    "同舟共济": 2,
    "见贤思齐": 2,
    "未雨绸缪": 2,
    "狐假虎威": 1,
    "风雨飘摇": 1,
    "天伦之乐": 1,
    "火上浇油": 1,
    "眉头紧锁": 1,
    "坚持不懈": 1,
    "鸡犬不宁": 1,
    "排山倒海": 1,
    "日新月异": 1,
    "众口铄金": 1,
    "晴天霹雳": 1,
    "百战百胜": 1,
    "百里挑一": 1,
    "礼尚往来": 1,
    "秀色可餐": 1,
    "小菜一碟": 1,
    "老无所依": 1,
    "劫后余生": 1,
    "心如止水": 1,
    "车水马龙": 1,
    "明知故犯": 1,
    "金石为开": 1,
    "旗开得胜": 1,
    "耳目一新": 1,
    "奇形怪状": 1,
    "金玉满堂": 1,
    "不求甚解": 1,
    "立竿见影": 1,
    "兵不厌诈": 1,
    "家长里短": 1,
    "继往开来": 1,
    "时来运转": 1,
    "小鸟依人": 1,
    "宁缺毋滥": 1,
    "宠辱不惊": 1,
    "扪心自问": 1,
    "饮鸩止渴": 1,
    "津津有味": 1,
    "七月流火": 1,
    "首当其冲": 1,
    "平心定气": 1,
    "蟾宫折桂": 1,
    "离经叛道": 1,
    "箭在弦上": 1,
    "不进则退": 1,
    "惊魂未定": 1,
    "临渊羡鱼": 1,
    "满目疮痍": 1,
    "沉鱼落雁": 1,
    "守株待兔": 1,
    "刻舟求剑": 1,
    "完璧归赵": 1,
    "筚路蓝缕": 1,
    "巧舌如簧": 1,
    "报仇雪恨": 1,
    "患得患失": 1,
    "乱七八糟": 1,
    "信手拈来": 1,
    "天道酬勤": 1,
    "杀身之祸": 1,
    "有的放矢": 1,
    "井然有序": 1,
    "汗流浃背": 1,
    "称兄道弟": 1,
    "废寝忘食": 1,
    "在劫难逃": 1,
    "一鼓作气": 1,
    "一马平川": 1
}